gzip_range_httpd/__init__.py
gzip_range_httpd/__main__.py
gzip_range_httpd-0.1.0.dist-info/METADATA
gzip_range_httpd-0.1.0.dist-info/WHEEL
gzip_range_httpd-0.1.0.dist-info/top_level.txt
gzip_range_httpd-0.1.0.dist-info/RECORD
