Metadata-Version: 2.1
Name: gzip-range-httpd
Version: 0.1.0
Summary: A simple HTTP server that supports gzip and range requests
Author-email: Andrei Paraschiv <andrei@thephpfactory.com>
License: Apache-2.0
Project-URL: Homepage, https://github.com/AndyTheFactory/GzipRangeSimpleHTTPServer
Project-URL: Repository, https://github.com/AndyTheFactory/GzipRangeSimpleHTTPServer.git
Project-URL: Issues, https://github.com/AndyTheFactory/GzipRangeSimpleHTTPServer/issues
Project-URL: Changelog, https://github.com/AndyTheFactory/GzipRangeSimpleHTTPServer/blob/master/CHANGELOG.md
Keywords: http,server,gzip,range
Classifier: Environment :: Console
Classifier: Environment :: Web Environment
Classifier: Development Status :: 4 - Beta
Classifier: Intended Audience :: Developers
Classifier: License :: OSI Approved :: Apache Software License
Requires-Python: >=3.8
